<?xml version="1.0" encoding="UTF-8"?>
<language xmlns="https://www.woltlab.com" xmlns:xsi="https://www.w3.org/2001/XMLSchema-instance" xsi:schemaLocation="https://www.woltlab.com https://www.woltlab.com/XSD/tornado/language.xsd" languagecode="de" languagename="Deutsch" countrycode="de">
	<category name="wcf.user.option">
        	<item name="wcf.user.option.eMarkaddress"><![CDATA[Deutsche eMark]]></item>
        	<item name="wcf.user.option.eMarkaddress.description"><![CDATA[{if LANGUAGE_USE_INFORMAL_VARIANT}Gib{else}Geben Sie{/if} <strong>hier {if LANGUAGE_USE_INFORMAL_VARIANT}deine{else}Ihre{/if} eMark Adresse</strong> (z.B. NSpendebUuNUsYcTeZNgsfLkZVQeeDj5AV) ein.<br/><strong>Achtung! Die eMark Adresse kann nachträglich nicht geändert werden!</strong>]]></item>
	</category>
	<category name="wcf.acp.option">
		<item name="wcf.acp.option.category.user.demprofilefieldoptions"><![CDATA[Deutsche eMark Profilfeld]]></item>
		<item name="wcf.acp.option.user_demprofilefieldoptions_showabout_enable"><![CDATA[eMark Profilfeld auf der "Über mich" Seite anzeigen?]]></item>
		<item name="wcf.acp.option.user_demprofilefieldoptions_showsidebar_enable"><![CDATA[eMark Profilfeld in der Sidebar-Auflistung anzeigen?]]></item>
		<item name="wcf.acp.option.message_sidebar_user_options_sidebardemprofilefield"><![CDATA[eMark Profilfeld anzeigen:]]></item>
	</category>
</language>
